chinese_pdf_divider/__init__.py
chinese_pdf_divider/pdf_divider.py
chinese_pdf_divider-1.1.0.dist-info/LICENSE.txt
chinese_pdf_divider-1.1.0.dist-info/METADATA
chinese_pdf_divider-1.1.0.dist-info/WHEEL
chinese_pdf_divider-1.1.0.dist-info/top_level.txt
chinese_pdf_divider-1.1.0.dist-info/RECORD
