Metadata-Version: 2.1
Name: chinese-pdf-divider
Version: 1.1.0
Summary: divide chinese pdf file into blocks within 512
Home-page: UNKNOWN
Author: yunsi lin
Author-email: yunsi0115@gmail.com
License: UNKNOWN
Platform: UNKNOWN
Classifier: License :: OSI Approved :: MIT License
Classifier: Programming Language :: Python :: 3
Classifier: Programming Language :: Python :: 3.10
License-File: LICENSE.txt
Requires-Dist: pymupdf
Requires-Dist: fitz
Requires-Dist: pandas
Requires-Dist: numpy
